Metadata-Version: 2.1
Name: neon-tts-plugin-larynx-server
Version: 0.2.1
Summary: Larynx tts plugin for OVOS / Neon / Mycroft
Home-page: https://github.com/NeonGeckoCom/neon-tts-plugin-larynx-server
Author: Neongecko
Author-email: developers@neon.ai
License: BSD 3
Keywords: mycroft ovos neon plugin tts
Classifier: Development Status :: 3 - Alpha
Classifier: Intended Audience :: Developers
Classifier: Topic :: Text Processing :: Linguistic
Classifier: License :: OSI Approved :: Apache Software License
Classifier: Programming Language :: Python :: 2
Classifier: Programming Language :: Python :: 2.7
Classifier: Programming Language :: Python :: 3
Classifier: Programming Language :: Python :: 3.0
Classifier: Programming Language :: Python :: 3.1
Classifier: Programming Language :: Python :: 3.2
Classifier: Programming Language :: Python :: 3.3
Classifier: Programming Language :: Python :: 3.4
Classifier: Programming Language :: Python :: 3.5
Classifier: Programming Language :: Python :: 3.6
License-File: LICENSE.md
Requires-Dist: ovos-plugin-manager>=0.0.12,~=0.0
Requires-Dist: SpeechRecognition~=3.8
Requires-Dist: requests~=2.26
